cellpy/__init__.py
cellpy/_version.py
cellpy/cli.py
cellpy/exceptions.py
cellpy/log.py
cellpy/logging.json
cellpy/internals/__init__.py
cellpy/internals/core.py
cellpy/internals/otherpath.py
cellpy/libs/__init__.py
cellpy/libs/apipkg/__init__.py
cellpy/libs/apipkg/_alias_module.py
cellpy/libs/apipkg/_importing.py
cellpy/libs/apipkg/_module.py
cellpy/libs/apipkg/_syncronized.py
cellpy/libs/apipkg/_version.py
cellpy/libs/apipkg/py.typed
cellpy/parameters/.cellpy_prms_default.conf
cellpy/parameters/__init__.py
cellpy/parameters/internal_settings.py
cellpy/parameters/prmreader.py
cellpy/parameters/prms.py
cellpy/parameters/legacy/__init__.py
cellpy/parameters/legacy/update_headers.py
cellpy/readers/__init__.py
cellpy/readers/cellreader.py
cellpy/readers/core.py
cellpy/readers/dbreader.py
cellpy/readers/do.py
cellpy/readers/filefinder.py
cellpy/readers/sql_dbreader.py
cellpy/readers/instruments/__init__.py
cellpy/readers/instruments/arbin_res.py
cellpy/readers/instruments/arbin_sql.py
cellpy/readers/instruments/arbin_sql_7.py
cellpy/readers/instruments/arbin_sql_csv.py
cellpy/readers/instruments/arbin_sql_h5.py
cellpy/readers/instruments/arbin_sql_xlsx.py
cellpy/readers/instruments/base.py
cellpy/readers/instruments/biologics_mpr.py
cellpy/readers/instruments/custom.py
cellpy/readers/instruments/ext_nda_reader.py
cellpy/readers/instruments/local_instrument.py
cellpy/readers/instruments/maccor_txt.py
cellpy/readers/instruments/neware_txt.py
cellpy/readers/instruments/neware_xlsx.py
cellpy/readers/instruments/pec_csv.py
cellpy/readers/instruments/configurations/__init__.py
cellpy/readers/instruments/configurations/maccor_txt_one.py
cellpy/readers/instruments/configurations/maccor_txt_three.py
cellpy/readers/instruments/configurations/maccor_txt_two.py
cellpy/readers/instruments/configurations/maccor_txt_zero.py
cellpy/readers/instruments/configurations/neware_txt_one.py
cellpy/readers/instruments/configurations/neware_txt_two.py
cellpy-1.0.2.post8.dist-info/licenses/AUTHORS.md
cellpy-1.0.2.post8.dist-info/licenses/LICENSE.md
cellpy-1.0.2.post8.dist-info/METADATA
cellpy-1.0.2.post8.dist-info/WHEEL
cellpy-1.0.2.post8.dist-info/entry_points.txt
cellpy-1.0.2.post8.dist-info/top_level.txt
cellpy-1.0.2.post8.dist-info/RECORD
