Metadata-Version: 2.4
Name: cellpy
Version: 1.0.2.post8
Summary: Extract and manipulate data from battery data testers.
Home-page: https://github.com/jepegit/cellpy
Author: Jan Petter Maehlen
Author-email: jepe@ife.no
License: MIT license
Keywords: cellpy
Classifier: Development Status :: 5 - Production/Stable
Classifier: Intended Audience :: Science/Research
Classifier: License :: OSI Approved :: MIT License
Classifier: Natural Language :: English
Classifier: Programming Language :: Python :: 3.10
Classifier: Programming Language :: Python :: 3.11
Classifier: Programming Language :: Python :: 3.12
Classifier: Programming Language :: Python :: 3.13
License-File: LICENSE.md
License-File: AUTHORS.md
Requires-Dist: scipy
Requires-Dist: numpy
Requires-Dist: pandas
Requires-Dist: python-box
Requires-Dist: setuptools
Requires-Dist: ruamel.yaml
Requires-Dist: matplotlib
Requires-Dist: openpyxl
Requires-Dist: click
Requires-Dist: PyGithub
Requires-Dist: tqdm
Requires-Dist: pint
Requires-Dist: requests
Requires-Dist: pyodbc
Requires-Dist: sqlalchemy>=2.0.0
Requires-Dist: sqlalchemy-access; platform_system == "windows"
Requires-Dist: python-dotenv
Requires-Dist: fabric
Requires-Dist: dateparser
Requires-Dist: cookiecutter
Requires-Dist: jinja2_time
Requires-Dist: tables
Requires-Dist: ipykernel
Requires-Dist: rich
Requires-Dist: charset-normalizer
Provides-Extra: batch
Requires-Dist: ipython; extra == "batch"
Requires-Dist: jupyter; extra == "batch"
Requires-Dist: plotly; extra == "batch"
Requires-Dist: seaborn; extra == "batch"
Requires-Dist: kaleido==0.1.*; extra == "batch"
Provides-Extra: fit
Requires-Dist: lmfit; extra == "fit"
Provides-Extra: all
Requires-Dist: ipython; extra == "all"
Requires-Dist: jupyter; extra == "all"
Requires-Dist: plotly; extra == "all"
Requires-Dist: seaborn; extra == "all"
Requires-Dist: kaleido==0.1.*; extra == "all"
Requires-Dist: lmfit; extra == "all"
Dynamic: author
Dynamic: author-email
Dynamic: classifier
Dynamic: description
Dynamic: description-content-type
Dynamic: home-page
Dynamic: keywords
Dynamic: license
Dynamic: license-file
Dynamic: provides-extra
Dynamic: requires-dist
Dynamic: summary
